{
    "russian_battalion_tactical_group": {
        "id": "russian_battalion_tactical_group",
        "name": "Russian BTG",
        "description": "",
        "faction": "russia",
        "branch": "mechanized",
        "icon": "russian_battalion_tactical_group",
        "attack": 2,
        "defense": 2,
        "movement": 4,
        "cost": 0,
        "fuel_consumption": 0,
        "frequency": 1
    },
    "russian_dpr_lpr_brigade": {
        "id": "russian_dpr_lpr_brigade",
        "name": "DPR/LPR Brigade",
        "description": "",
        "faction": "russia",
        "branch": "infantry",
        "icon": "russian_dpr_lpr_brigade",
        "attack": 1,
        "defense": 2,
        "movement": 2,
        "cost": 0,
        "fuel_consumption": 0,
        "frequency": 1
    },
    "russian_auxiliary": {
        "id": "russian_auxiliary",
        "name": "Russian Auxiliary",
        "description": "",
        "faction": "russia",
        "branch": "infantry",
        "icon": "russian_auxiliary",
        "attack": 1,
        "defense": 2,
        "movement": 1,
        "cost": 0,
        "fuel_consumption": 0,
        "frequency": 1
    },
    "russian_infantry": {
        "id": "russian_infantry",
        "name": "Russian Infantry",
        "description": "",
        "faction": "russia",
        "branch": "infantry",
        "icon": "russian_infantry",
        "attack": 2,
        "defense": 2,
        "movement": 2,
        "cost": 0,
        "fuel_consumption": 0,
        "frequency": 1     
    },
    "russian_wagner": {
        "id": "russian_wagner",
        "name": "Wagner PMC",
        "description": "",
        "faction": "russia",
        "branch": "infantry",
        "icon": "russian_wagner",
        "attack": 3,
        "defense": 3,
        "movement": 3,
        "cost": 0,
        "fuel_consumption": 0,
        "frequency": 1
    },
    "russian_fortification": {
        "id": "russian_fortification",
        "name": "Russian Fortification",
        "description": "",
        "faction": "russia",
        "branch": "fortification",
        "icon": "russian_fortification",
        "attack": 0,
        "defense": 3,
        "movement": 0,
        "cost": 0,
        "fuel_consumption": 0,
        "frequency": 1
    },
    "ukrainian_conscripts": {
        "id": "ukrainian_conscripts",
        "name": "Ukrainian Conscripts",
        "description": "",
        "faction": "ukraine",
        "branch": "infantry",
        "icon": "ukrainian_conscripts",
        "attack": 1,
        "defense": 2,
        "movement": 2,
        "cost": 0,
        "fuel_consumption": 0,
        "frequency": 1     
    },
    "ukrainian_territorial_defense": {
        "id": "ukrainian_territorial_defense",
        "name": "Ukrainian Territorial Defense",
        "description": "",
        "faction": "ukraine",
        "branch": "infantry",
        "icon": "ukrainian_territorial_defense",
        "attack": 1,
        "defense": 1,
        "movement": 2,
        "cost": 0,
        "fuel_consumption": 0,
        "frequency": 1      
    },
    "ukrainian_infantry": {
        "id": "ukrainian_infantry",
        "name": "Ukrainian Infantry",
        "description": "",
        "faction": "ukraine",
        "branch": "infantry",
        "icon": "ukrainian_infantry",
        "attack": 2,
        "defense": 2,
        "movement": 2,
        "cost": 0,
        "fuel_consumption": 0,
        "frequency": 1    
    },
    "ukrainian_nato_brigade": {
        "id": "ukrainian_nato_brigade",
        "name": "Ukrainian NATO Brigade",
        "description": "",
        "faction": "ukraine",
        "branch": "mechanized",
        "icon": "ukrainian_nato_brigade",
        "attack": 2,
        "defense": 3,
        "movement": 2,
        "cost": 0,
        "fuel_consumption": 0,
        "frequency": 1
    },
    "ukrainian_fortification": {
        "id": "ukrainian_fortification",
        "name": "Ukrainian Fortification",
        "description": "",
        "faction": "ukraine",
        "branch": "fortification",
        "icon": "ukrainian_fortification",
        "attack": 0,
        "defense": 3,
        "movement": 0,
        "cost": 0,
        "fuel_consumption": 0,
        "frequency": 1
    }
}